geode_conversion/__init__.py
geode_conversion/__init__.pyi
geode_conversion/model_conversion.py
geode_conversion/model_conversion.pyi
geode_conversion/py.typed
geode_conversion/lib64/__init__.pyi
geode_conversion/lib64/geode_conversion_py_model.cpython-310-x86_64-linux-gnu.so
geode_conversion/lib64/geode_conversion_py_model.pyi
geode_conversion/lib64/libGeode-Conversion_model.so
geode_conversion-6.5.9.dist-info/METADATA
geode_conversion-6.5.9.dist-info/WHEEL
geode_conversion-6.5.9.dist-info/top_level.txt
geode_conversion-6.5.9.dist-info/RECORD
