Metadata-Version: 2.4
Name: Geode-Conversion
Version: 6.5.9
Summary: Conversion module for Geode-solutions OpenGeode modules
Author-email: Geode-solutions <contact@geode-solutions.com>
License: Proprietary
Requires-Python: <3.13,>=3.9
Requires-Dist: geode-common==33.*,>=33.14.4
Requires-Dist: opengeode-core==15.*,>=15.30.10
